get_time_practice/__init__.py
get_time_practice-0.0.4.dist-info/METADATA
get_time_practice-0.0.4.dist-info/WHEEL
get_time_practice-0.0.4.dist-info/entry_points.txt
get_time_practice-0.0.4.dist-info/top_level.txt
get_time_practice-0.0.4.dist-info/RECORD
