Metadata-Version: 2.2
Name: get-time-practice
Version: 0.0.4
Summary: 获取任意时间/获取当前的时间戳/时间转时间戳/时间戳转时间
Home-page: https://github.com/Coxhuang/get_time
Author: 测试
Author-email: gmhesat@gmail.com
Dynamic: author
Dynamic: author-email
Dynamic: home-page
Dynamic: summary
